upgrade_ensurepip/__init__.py
upgrade_ensurepip/__main__.py
upgrade_ensurepip/upgrade_ensurepip.py
upgrade_ensurepip-0.2.1.dist-info/LICENSE
upgrade_ensurepip-0.2.1.dist-info/METADATA
upgrade_ensurepip-0.2.1.dist-info/WHEEL
upgrade_ensurepip-0.2.1.dist-info/entry_points.txt
upgrade_ensurepip-0.2.1.dist-info/namespace_packages.txt
upgrade_ensurepip-0.2.1.dist-info/top_level.txt
upgrade_ensurepip-0.2.1.dist-info/RECORD
